winservicetools/__init__.py
winservicetools/__version__.py
winservicetools/cli.py
winservicetools/utils.py
winservicetools-0.8.0.dist-info/METADATA
winservicetools-0.8.0.dist-info/WHEEL
winservicetools-0.8.0.dist-info/entry_points.txt
winservicetools-0.8.0.dist-info/top_level.txt
winservicetools-0.8.0.dist-info/RECORD
