Metadata-Version: 2.1
Name: winservicetools
Version: 0.8.0
Summary: Run Python Based Windows Services Easily
Home-page: https://github.com/mechsin/winservicetools
Author: Christopher Nyland
Author-email: menyland@gmail.com
License: MIT License
Project-URL: Source Code, https://github.com/mechsin/winservicetools
Platform: Windows
Classifier: Intended Audience :: Developers
Classifier: Intended Audience :: System Administrators
Classifier: License :: OSI Approved :: MIT License
Classifier: Natural Language :: English
Classifier: Operating System :: Microsoft :: Windows
Classifier: Programming Language :: Python :: 3
Classifier: Topic :: Utilities
Classifier: Topic :: System :: Systems Administration
Requires-Dist: pywin32
